<annotation>
	<folder>png</folder>
	<filename>f9.jpg</filename>
	<path>C:\Users\Arjun\Downloads\png\f9.jpg</path>
	<source>
		<database>Unknown</database>
	</source>
	<size>
		<width>1400</width>
		<height>761</height>
		<depth>3</depth>
	</size>
	<segmented>0</segmented>
	<object>
		<name>pillar</name>
		<pose>Unspecified</pose>
		<truncated>0</truncated>
		<difficult>0</difficult>
		<bndbox>
			<xmin>94</xmin>
			<ymin>463</ymin>
			<xmax>140</xmax>
			<ymax>697</ymax>
		</bndbox>
	</object>
	<object>
		<name>pillar</name>
		<pose>Unspecified</pose>
		<truncated>0</truncated>
		<difficult>0</difficult>
		<bndbox>
			<xmin>1314</xmin>
			<ymin>460</ymin>
			<xmax>1354</xmax>
			<ymax>684</ymax>
		</bndbox>
	</object>
	<object>
		<name>truck</name>
		<pose>Unspecified</pose>
		<truncated>0</truncated>
		<difficult>0</difficult>
		<bndbox>
			<xmin>179</xmin>
			<ymin>290</ymin>
			<xmax>1264</xmax>
			<ymax>708</ymax>
		</bndbox>
	</object>
</annotation>
