<annotation>
	<folder>New folder</folder>
	<filename>line477.jpg</filename>
	<path>E:\Cygnet\Python\Yolo - Copy\darkflow-master\New folder\line477.jpg</path>
	<source>
		<database>Unknown</database>
	</source>
	<size>
		<width>225</width>
		<height>300</height>
		<depth>3</depth>
	</size>
	<segmented>0</segmented>
	<object>
		<name>pillar</name>
		<pose>Unspecified</pose>
		<truncated>0</truncated>
		<difficult>0</difficult>
		<bndbox>
			<xmin>118</xmin>
			<ymin>28</ymin>
			<xmax>162</xmax>
			<ymax>245</ymax>
		</bndbox>
	</object>
</annotation>
